djvue/__init__.py
djvue/apps.py
djvue/defaults.py
djvue/fields.py
djvue/serializers.py
djvue/urls.py
djvue/validators.py
djvue/views.py
djvue/vv_locale.py
djvue/static/vue/js/axios.js
djvue/static/vue/js/lodash.js
djvue/static/vue/js/script.js
djvue/static/vue/js/vee-validate.full.js
djvue/static/vue/js/vue.js
djvue/templates/vue/starter.html
djvue/templates/vue/default/checkbox.html
djvue/templates/vue/default/checkbox_multiple.html
djvue/templates/vue/default/dict_field.html
djvue/templates/vue/default/fieldset.html
djvue/templates/vue/default/file.html
djvue/templates/vue/default/file_multiple.html
djvue/templates/vue/default/form.html
djvue/templates/vue/default/input.html
djvue/templates/vue/default/list_field.html
djvue/templates/vue/default/list_fieldset.html
djvue/templates/vue/default/radio.html
djvue/templates/vue/default/select.html
djvue/templates/vue/default/select_multiple.html
djvue/templates/vue/default/textarea.html
djvue/templatetags/__init__.py
djvue/templatetags/vue_tags.py
djvue-0.2.1.dist-info/AUTHORS.rst
djvue-0.2.1.dist-info/LICENSE
djvue-0.2.1.dist-info/METADATA
djvue-0.2.1.dist-info/WHEEL
djvue-0.2.1.dist-info/top_level.txt
djvue-0.2.1.dist-info/RECORD
