Metadata-Version: 1.1
Name: djvue
Version: 0.2.1
Summary:  Mix Vue.js with DRF form renderer in Django templates
Home-page: https://github.com/KuwaitNET/djvue
Author: Dacian Popute
Author-email: dacian@kuwaitnet.com
License: MIT
Keywords: djvue
Platform: UNKNOWN
Classifier: Development Status :: 3 - Alpha
Classifier: Framework :: Django :: 2.2
Classifier: Intended Audience :: Developers
Classifier: License :: OSI Approved :: BSD License
Classifier: Natural Language :: English
Classifier: Programming Language :: Python :: 2
Classifier: Programming Language :: Python :: 2.7
Classifier: Programming Language :: Python :: 3
Classifier: Programming Language :: Python :: 3.5
Classifier: Programming Language :: Python :: 3.6
